parserkiosk/__init__.py
parserkiosk/colors.py
parserkiosk/parserkiosk.py
parserkiosk/schema.py
parserkiosk/schemas/__init__.py
parserkiosk/schemas/config_schema.yaml
parserkiosk/schemas/test_schema.yaml
parserkiosk/templates/__init__.py
parserkiosk/templates/node_js.jinja2
parserkiosk/templates/python.jinja2
parserkiosk/util.py
parserkiosk-0.3.0.dist-info/entry_points.txt
parserkiosk-0.3.0.dist-info/LICENSE.md
parserkiosk-0.3.0.dist-info/WHEEL
parserkiosk-0.3.0.dist-info/METADATA
parserkiosk-0.3.0.dist-info/RECORD
