Metadata-Version: 2.1
Name: parserkiosk
Version: 0.3.0
Summary: A Proof of Concept multi-lingual test generation suite intended for parsers.
Home-page: https://github.com/R9295/parser-kiosk
License: GPL-3.0
Keywords: Parsers,Parser,Code Generation,Testing
Author: aarnav
Author-email: aarnavbos@gmail.com
Requires-Python: >=3.10,<4.0
Classifier: License :: OSI Approved :: GNU General Public License v3 (GPLv3)
Classifier: Operating System :: OS Independent
Classifier: Programming Language :: Python :: 3
Classifier: Programming Language :: Python :: 3.10
Classifier: Topic :: Software Development :: Testing
Requires-Dist: Jinja2 (>=3.0.3,<4.0.0)
Requires-Dist: PyYAML (>=6.0,<7.0)
Requires-Dist: python-box (>=5.4.1,<6.0.0)
Requires-Dist: yamale (>=4.0.4,<5.0.0)
Project-URL: Documentation, https://github.com/R9295/parser-kiosk
Project-URL: Repository, https://github.com/R9295/parser-kiosk
